cappr/__init__.py
cappr/_example.py
cappr/huggingface/__init__.py
cappr/huggingface/_patch_tokenizer.py
cappr/huggingface/_utils.py
cappr/huggingface/classify.py
cappr/huggingface/classify_no_cache.py
cappr/llama_cpp/__init__.py
cappr/llama_cpp/_classify_no_cache.py
cappr/llama_cpp/_utils.py
cappr/llama_cpp/classify.py
cappr/openai/__init__.py
cappr/openai/api.py
cappr/openai/classify.py
cappr/utils/__init__.py
cappr/utils/_batch.py
cappr/utils/_check.py
cappr/utils/_no_cache.py
cappr/utils/classify.py
cappr-0.9.6.dist-info/LICENSE
cappr-0.9.6.dist-info/METADATA
cappr-0.9.6.dist-info/WHEEL
cappr-0.9.6.dist-info/top_level.txt
cappr-0.9.6.dist-info/RECORD
