Metadata-Version: 2.1
Name: cappr
Version: 0.9.6
Summary: Completion After Prompt Probability. Make your LLM make a choice
Author-email: Kush Dubey <kushdubey63@gmail.com>
Maintainer-email: Kush Dubey <kushdubey63@gmail.com>
License: Apache License
Project-URL: Homepage, https://github.com/kddubey/cappr
Project-URL: Documentation, https://cappr.readthedocs.io/en/latest/
Project-URL: Issues, https://github.com/kddubey/cappr/issues
Classifier: Programming Language :: Python :: 3
Classifier: Programming Language :: Python :: 3.8
Classifier: Programming Language :: Python :: 3.9
Classifier: Programming Language :: Python :: 3.10
Classifier: Programming Language :: Python :: 3.11
Classifier: Programming Language :: Python :: 3.12
Requires-Python: >=3.8
License-File: LICENSE
Requires-Dist: numpy >=1.21.0
Requires-Dist: tqdm >=4.27.0
Provides-Extra: all
Requires-Dist: cappr[hf,llama-cpp,openai] ; extra == 'all'
Provides-Extra: demos
Requires-Dist: cappr[hf-dev,llama-cpp-dev,openai] ; extra == 'demos'
Requires-Dist: datasets >=2.10.0 ; extra == 'demos'
Requires-Dist: jupyter >=1.0.0 ; extra == 'demos'
Requires-Dist: matplotlib >=3.7.3 ; extra == 'demos'
Requires-Dist: pandas >=1.5.3 ; extra == 'demos'
Requires-Dist: scikit-learn >=1.2.2 ; extra == 'demos'
Provides-Extra: dev
Requires-Dist: cappr[demos] ; extra == 'dev'
Requires-Dist: docutils <0.19 ; extra == 'dev'
Requires-Dist: pre-commit >=3.5.0 ; extra == 'dev'
Requires-Dist: pydata-sphinx-theme >=0.13.1 ; extra == 'dev'
Requires-Dist: pytest >=7.2.1 ; extra == 'dev'
Requires-Dist: pytest-cov >=4.0.0 ; extra == 'dev'
Requires-Dist: pytest-sugar >=1.0.0 ; extra == 'dev'
Requires-Dist: ruff >=0.7.0 ; extra == 'dev'
Requires-Dist: sphinx >=6.1.3 ; extra == 'dev'
Requires-Dist: sphinx-copybutton >=0.5.2 ; extra == 'dev'
Requires-Dist: sphinx-togglebutton >=0.3.2 ; extra == 'dev'
Requires-Dist: sphinxcontrib-napoleon >=0.7 ; extra == 'dev'
Requires-Dist: twine >=4.0.2 ; extra == 'dev'
Provides-Extra: hf
Requires-Dist: transformers[torch] >=4.31.0 ; extra == 'hf'
Provides-Extra: hf-dev
Requires-Dist: huggingface-hub >=0.16.4 ; extra == 'hf-dev'
Requires-Dist: peft >=0.13.2 ; extra == 'hf-dev'
Requires-Dist: protobuf >=5.27.2 ; extra == 'hf-dev'
Requires-Dist: sentencepiece >=0.1.99 ; extra == 'hf-dev'
Requires-Dist: transformers[torch] >=4.35.0 ; extra == 'hf-dev'
Provides-Extra: llama-cpp
Requires-Dist: llama-cpp-python >=0.2.11 ; extra == 'llama-cpp'
Provides-Extra: llama-cpp-dev
Requires-Dist: llama-cpp-python >=0.2.13 ; extra == 'llama-cpp-dev'
Provides-Extra: openai
Requires-Dist: openai >=0.26.0 ; extra == 'openai'
Requires-Dist: tiktoken >=0.2.0 ; extra == 'openai'
